{"success":true,"excelData":[{"🔍 MASTER SEARCH DASHBOARD":"SEARCH INPUT"},{"🔍 MASTER SEARCH DASHBOARD":"Search Term:","__EMPTY":"introduction to management"},{"🔍 MASTER SEARCH DASHBOARD":"College Filter:","__EMPTY":"ALL"},{"🔍 MASTER SEARCH DASHBOARD":"Country Filter:","__EMPTY":"ALL"},{"🔍 MASTER SEARCH DASHBOARD":"SEARCH RESULTS"},{"🔍 MASTER SEARCH DASHBOARD":"Type","__EMPTY":"Code/ID","__EMPTY_1":"Name/Title","__EMPTY_2":"Institution/Country","__EMPTY_3":"Level/College","__EMPTY_4":"Credits/Ranking","__EMPTY_5":"Status","__EMPTY_6":"Action"},{"🔍 MASTER SEARCH DASHBOARD":false,"__EMPTY":"","__EMPTY_1":"","__EMPTY_2":"","__EMPTY_3":"","__EMPTY_4":"","__EMPTY_5":"","__EMPTY_6":""},{"🔍 MASTER SEARCH DASHBOARD":"","__EMPTY":"","__EMPTY_1":"","__EMPTY_2":"","__EMPTY_3":"","__EMPTY_4":"","__EMPTY_5":"","__EMPTY_6":""},{"🔍 MASTER SEARCH DASHBOARD":"","__EMPTY":"","__EMPTY_1":"","__EMPTY_2":"","__EMPTY_3":"","__EMPTY_4":"","__EMPTY_5":"","__EMPTY_6":""},{"🔍 MASTER SEARCH DASHBOARD":"CREDIT CONVERTER","__EMPTY_4":"LIVE STATISTICS"},{"🔍 MASTER SEARCH DASHBOARD":"Partner Credits:","__EMPTY_3":"DATABASE STATISTICS","__EMPTY_4":"Total Mappings:","__EMPTY_5":441},{"🔍 MASTER SEARCH DASHBOARD":"Credit System:","__EMPTY_3":"DATABASE STATISTICS","__EMPTY_4":1,"__EMPTY_5":0,"__EMPTY_6":"🔍 SEARCH GUIDE"},{"__EMPTY_3":"Total Course Mappings:","__EMPTY_4":1,"__EMPTY_5":2},{"🔍 MASTER SEARCH DASHBOARD":"Ajman Credits:","__EMPTY":"","__EMPTY_3":"Partner Universities:","__EMPTY_4":49,"__EMPTY_5":0,"__EMPTY_6":"QUICK START:"},{"__EMPTY_3":"Ajman Courses:","__EMPTY_4":3,"__EMPTY_5":49,"__EMPTY_6":"• Type in the blue search box (B5)"},{"__EMPTY_3":"Countries Covered:","__EMPTY_4":1,"__EMPTY_5":0,"__EMPTY_6":"• Results appear automatically"},{"__EMPTY_6":"• Search works across all data"},{"__EMPTY_6":"🔍 ENHANCED SEARCH GUIDE"},{"__EMPTY_6":"SEARCH EXAMPLES:"},{"__EMPTY_6":"• 'Jindal' → finds O. P. Jindal Global University"},{"__EMPTY_6":"• 'Malaysia' → finds Malaysian universities"},{"__EMPTY_6":"• 'Management' → finds management courses"},{"__EMPTY_6":"• 'India' → finds all Indian universities"},{"__EMPTY_6":"• 'USA' → finds American universities"},{"__EMPTY_6":"• 'Programming' → finds programming courses"},{"__EMPTY_6":"• 'Toronto' → finds University of Toronto"},{"__EMPTY_6":"DATABASE NOW INCLUDES:"},{"__EMPTY_6":"• 49 Partner Universities"},{"__EMPTY_6":"• 20 Countries"},{"__EMPTY_6":"• Real-time search across all data"},{"__EMPTY_6":"• No more N/A errors!"}],"timestamp":"2025-09-29T10:48:15.445Z"}